{
  "updated_at": "2026-03-04T20:29:23.874364+09:00",
  "count": 32,
  "trends": [
    {
      "title": "日経平均3日続落、2033円安の5万4245円で着地",
      "post_count": 14494,
      "category": "",
      "time_ago": "",
      "source": "X ニューストレンド",
      "origin": "x_news"
    },
    {
      "title": "SBI北尾社長、AI活用で新卒採用を大幅削減へ",
      "post_count": 1868,
      "category": "",
      "time_ago": "",
      "source": "X ニューストレンド",
      "origin": "x_news"
    },
    {
      "title": "イラン拘束のNHKテヘラン支局長、無事を確認　政府が発表",
      "post_count": 1518,
      "category": "",
      "time_ago": "",
      "source": "X ニューストレンド",
      "origin": "x_news"
    },
    {
      "title": "オープンAI、国防総省契約を修正　アルトマンCEOが「間違い」と釈明",
      "post_count": 628,
      "category": "",
      "time_ago": "",
      "source": "X ニューストレンド",
      "origin": "x_news"
    },
    {
      "title": "イラン攻撃後、取引所から1030万ドル相当のビットコイン流出",
      "post_count": 175,
      "category": "",
      "time_ago": "",
      "source": "X ニューストレンド",
      "origin": "x_news"
    },
    {
      "title": "ブロックチェーン",
      "post_count": 0,
      "category": "ビジネス・金融 · トレンド",
      "time_ago": "",
      "source": "X ニューストレンド",
      "origin": "x_news"
    },
    {
      "title": "moomoo証券",
      "post_count": 0,
      "category": "ビジネス・金融 · トレンド",
      "time_ago": "",
      "source": "X ニューストレンド",
      "origin": "x_news"
    },
    {
      "title": "三菱HCC",
      "post_count": 0,
      "category": "ビジネス・金融 · トレンド",
      "time_ago": "",
      "source": "X ニューストレンド",
      "origin": "x_news"
    },
    {
      "title": "ブリヂストン",
      "post_count": 0,
      "category": "ビジネス・金融 · トレンド",
      "time_ago": "",
      "source": "X ニューストレンド",
      "origin": "x_news"
    },
    {
      "title": "東京海上",
      "post_count": 0,
      "category": "ビジネス・金融 · トレンド",
      "time_ago": "",
      "source": "X ニューストレンド",
      "origin": "x_news"
    },
    {
      "title": "積水ハウス",
      "post_count": 0,
      "category": "ビジネス・金融 · トレンド",
      "time_ago": "",
      "source": "X ニューストレンド",
      "origin": "x_news"
    },
    {
      "title": "FANG",
      "post_count": 0,
      "category": "ビジネス・金融 · トレンド",
      "time_ago": "",
      "source": "X ニューストレンド",
      "origin": "x_news"
    },
    {
      "title": "配当利回り",
      "post_count": 0,
      "category": "ビジネス・金融 · トレンド",
      "time_ago": "",
      "source": "X ニューストレンド",
      "origin": "x_news"
    },
    {
      "title": "#TradeNote",
      "post_count": 0,
      "category": "ビジネス・金融 · トレンド",
      "time_ago": "",
      "source": "X ニューストレンド",
      "origin": "x_news"
    },
    {
      "title": "ステーブルコイン",
      "post_count": 0,
      "category": "ビジネス・金融 · トレンド",
      "time_ago": "",
      "source": "X ニューストレンド",
      "origin": "x_news"
    },
    {
      "title": "口座開設",
      "post_count": 0,
      "category": "ビジネス・金融 · トレンド",
      "time_ago": "",
      "source": "X ニューストレンド",
      "origin": "x_news"
    },
    {
      "title": "Amazon",
      "post_count": 0,
      "category": "ビジネス・金融 · トレンド",
      "time_ago": "",
      "source": "X ニューストレンド",
      "origin": "x_news"
    },
    {
      "title": "#カビュウ",
      "post_count": 0,
      "category": "ビジネス・金融 · トレンド",
      "time_ago": "",
      "source": "X ニューストレンド",
      "origin": "x_news"
    },
    {
      "title": "新生活先行セール",
      "post_count": 0,
      "category": "ビジネス・金融 · トレンド",
      "time_ago": "",
      "source": "X ニューストレンド",
      "origin": "x_news"
    },
    {
      "title": "溝口さん",
      "post_count": 0,
      "category": "ビジネス・金融 · トレンド",
      "time_ago": "",
      "source": "X ニューストレンド",
      "origin": "x_news"
    },
    {
      "title": "#NISA",
      "post_count": 0,
      "category": "ビジネス・金融 · トレンド",
      "time_ago": "",
      "source": "X ニューストレンド",
      "origin": "x_news"
    },
    {
      "title": "XAUUSD",
      "post_count": 0,
      "category": "ビジネス・金融 · トレンド",
      "time_ago": "",
      "source": "X ニューストレンド",
      "origin": "x_news"
    },
    {
      "title": "#株クラ",
      "post_count": 0,
      "category": "ビジネス・金融 · トレンド",
      "time_ago": "",
      "source": "X ニューストレンド",
      "origin": "x_news"
    },
    {
      "title": "三菱商事",
      "post_count": 0,
      "category": "ビジネス・金融 · トレンド",
      "time_ago": "",
      "source": "X ニューストレンド",
      "origin": "x_news"
    },
    {
      "title": "ホールド",
      "post_count": 0,
      "category": "ビジネス・金融 · トレンド",
      "time_ago": "",
      "source": "X ニューストレンド",
      "origin": "x_news"
    },
    {
      "title": "新規登録",
      "post_count": 0,
      "category": "ビジネス・金融 · トレンド",
      "time_ago": "",
      "source": "X ニューストレンド",
      "origin": "x_news"
    },
    {
      "title": "#高配当株",
      "post_count": 0,
      "category": "ビジネス・金融 · トレンド",
      "time_ago": "",
      "source": "X ニューストレンド",
      "origin": "x_news"
    },
    {
      "title": "日本製鉄",
      "post_count": 0,
      "category": "ビジネス・金融 · トレンド",
      "time_ago": "",
      "source": "X ニューストレンド",
      "origin": "x_news"
    },
    {
      "title": "日経VI",
      "post_count": 0,
      "category": "ビジネス・金融 · トレンド",
      "time_ago": "",
      "source": "X ニューストレンド",
      "origin": "x_news"
    },
    {
      "title": "#株式投資",
      "post_count": 0,
      "category": "ビジネス・金融 · トレンド",
      "time_ago": "",
      "source": "X ニューストレンド",
      "origin": "x_news"
    },
    {
      "title": "信用取引",
      "post_count": 0,
      "category": "ビジネス・金融 · トレンド",
      "time_ago": "",
      "source": "X ニューストレンド",
      "origin": "x_news"
    },
    {
      "title": "#デイトレ",
      "post_count": 0,
      "category": "ビジネス・金融 · トレンド",
      "time_ago": "",
      "source": "X ニューストレンド",
      "origin": "x_news"
    }
  ]
}