{
  "updated_at": "2026-03-05T12:29:22.288196+09:00",
  "count": 27,
  "trends": [
    {
      "title": "高市首相名を冠した仮想通貨「SANAE TOKEN」が無登録で問題、金融庁が調査へ",
      "post_count": 402785,
      "category": "",
      "time_ago": "",
      "source": "X ニューストレンド",
      "origin": "x_news"
    },
    {
      "title": "品川駅がラッシュ時に大混雑 横須賀線人身事故が原因",
      "post_count": 32250,
      "category": "",
      "time_ago": "",
      "source": "X ニューストレンド",
      "origin": "x_news"
    },
    {
      "title": "ホルムズ海峡封鎖で原油高騰、日本は254日備蓄で耐えられる",
      "post_count": 6273,
      "category": "",
      "time_ago": "",
      "source": "X ニューストレンド",
      "origin": "x_news"
    },
    {
      "title": "米潜水艦、イラン艦をインド洋で魚雷撃沈 乗員80人以上死亡",
      "post_count": 1219,
      "category": "",
      "time_ago": "",
      "source": "X ニューストレンド",
      "origin": "x_news"
    },
    {
      "title": "ホルムズ海峡封鎖で原油10％超急騰、タンカー150隻立ち往生",
      "post_count": 592,
      "category": "",
      "time_ago": "",
      "source": "X ニューストレンド",
      "origin": "x_news"
    },
    {
      "title": "FANG",
      "post_count": 0,
      "category": "ビジネス・金融 · トレンド",
      "time_ago": "",
      "source": "X ニューストレンド",
      "origin": "x_news"
    },
    {
      "title": "ミームコイン",
      "post_count": 0,
      "category": "ビジネス・金融 · トレンド",
      "time_ago": "",
      "source": "X ニューストレンド",
      "origin": "x_news"
    },
    {
      "title": "#日経平均",
      "post_count": 0,
      "category": "ビジネス・金融 · トレンド",
      "time_ago": "",
      "source": "X ニューストレンド",
      "origin": "x_news"
    },
    {
      "title": "買い戻し",
      "post_count": 0,
      "category": "ビジネス・金融 · トレンド",
      "time_ago": "",
      "source": "X ニューストレンド",
      "origin": "x_news"
    },
    {
      "title": "株式市場",
      "post_count": 0,
      "category": "ビジネス・金融 · トレンド",
      "time_ago": "",
      "source": "X ニューストレンド",
      "origin": "x_news"
    },
    {
      "title": "米国市場",
      "post_count": 0,
      "category": "ビジネス・金融 · トレンド",
      "time_ago": "",
      "source": "X ニューストレンド",
      "origin": "x_news"
    },
    {
      "title": "スマホ代",
      "post_count": 0,
      "category": "ビジネス・金融 · トレンド",
      "time_ago": "",
      "source": "X ニューストレンド",
      "origin": "x_news"
    },
    {
      "title": "積水ハウス",
      "post_count": 0,
      "category": "ビジネス・金融 · トレンド",
      "time_ago": "",
      "source": "X ニューストレンド",
      "origin": "x_news"
    },
    {
      "title": "口座開設",
      "post_count": 0,
      "category": "ビジネス・金融 · トレンド",
      "time_ago": "",
      "source": "X ニューストレンド",
      "origin": "x_news"
    },
    {
      "title": "買い増し",
      "post_count": 0,
      "category": "ビジネス・金融 · トレンド",
      "time_ago": "",
      "source": "X ニューストレンド",
      "origin": "x_news"
    },
    {
      "title": "#アマゾン",
      "post_count": 0,
      "category": "ビジネス・金融 · トレンド",
      "time_ago": "",
      "source": "X ニューストレンド",
      "origin": "x_news"
    },
    {
      "title": "ナスダック",
      "post_count": 0,
      "category": "ビジネス・金融 · トレンド",
      "time_ago": "",
      "source": "X ニューストレンド",
      "origin": "x_news"
    },
    {
      "title": "溝口さん",
      "post_count": 0,
      "category": "ビジネス・金融 · トレンド",
      "time_ago": "",
      "source": "X ニューストレンド",
      "origin": "x_news"
    },
    {
      "title": "moomoo証券",
      "post_count": 0,
      "category": "ビジネス・金融 · トレンド",
      "time_ago": "",
      "source": "X ニューストレンド",
      "origin": "x_news"
    },
    {
      "title": "安全資産",
      "post_count": 0,
      "category": "ビジネス・金融 · トレンド",
      "time_ago": "",
      "source": "X ニューストレンド",
      "origin": "x_news"
    },
    {
      "title": "#デイトレ",
      "post_count": 0,
      "category": "ビジネス・金融 · トレンド",
      "time_ago": "",
      "source": "X ニューストレンド",
      "origin": "x_news"
    },
    {
      "title": "寄り付き",
      "post_count": 0,
      "category": "ビジネス・金融 · トレンド",
      "time_ago": "",
      "source": "X ニューストレンド",
      "origin": "x_news"
    },
    {
      "title": "リバウンド",
      "post_count": 0,
      "category": "ビジネス・金融 · トレンド",
      "time_ago": "",
      "source": "X ニューストレンド",
      "origin": "x_news"
    },
    {
      "title": "原油価格",
      "post_count": 0,
      "category": "ビジネス・金融 · トレンド",
      "time_ago": "",
      "source": "X ニューストレンド",
      "origin": "x_news"
    },
    {
      "title": "プラネット",
      "post_count": 0,
      "category": "ビジネス・金融 · トレンド",
      "time_ago": "",
      "source": "X ニューストレンド",
      "origin": "x_news"
    },
    {
      "title": "KOSPI",
      "post_count": 0,
      "category": "ビジネス・金融 · トレンド",
      "time_ago": "",
      "source": "X ニューストレンド",
      "origin": "x_news"
    },
    {
      "title": "#株式投資",
      "post_count": 0,
      "category": "ビジネス・金融 · トレンド",
      "time_ago": "",
      "source": "X ニューストレンド",
      "origin": "x_news"
    }
  ]
}